torchline/__init__.py
torchline/config/__init__.py
torchline/config/config.py
torchline/config/default.py
torchline/data/__init__.py
torchline/data/albumentaion_transforms.py
torchline/data/autoaugment.py
torchline/data/build.py
torchline/data/common_datasets.py
torchline/data/sampler.py
torchline/data/transforms.py
torchline/engine/__init__.py
torchline/engine/build.py
torchline/engine/default_module.py
torchline/engine/utils.py
torchline/losses/__init__.py
torchline/losses/build.py
torchline/losses/focal_loss.py
torchline/losses/loss.py
torchline/models/__init__.py
torchline/models/build.py
torchline/models/dpn.py
torchline/models/efficientnet.py
torchline/models/mnasnet.py
torchline/models/mobilenet.py
torchline/models/nas_models.py
torchline/models/pnasnet.py
torchline/models/resnet.py
torchline/trainer/__init__.py
torchline/trainer/build.py
torchline/trainer/default_trainer.py
torchline/utils/__init__.py
torchline/utils/average_meter.py
torchline/utils/logger.py
torchline/utils/registry.py
torchline/utils/utils.py
torchline-0.3.0.4.dist-info/LICENSE
torchline-0.3.0.4.dist-info/METADATA
torchline-0.3.0.4.dist-info/WHEEL
torchline-0.3.0.4.dist-info/top_level.txt
torchline-0.3.0.4.dist-info/RECORD
