Metadata-Version: 2.1
Name: torchline
Version: 0.3.0.4
Summary: A framework for easy to use Pytorch
Home-page: https://github.com/marsggbo/torchline
Author: marsggbo
Author-email: csxinhe@comp.hkbu.edu.hk
License: UNKNOWN
Platform: UNKNOWN
Classifier: Programming Language :: Python :: 3
Classifier: License :: OSI Approved :: MIT License
Classifier: Operating System :: OS Independent
Requires-Python: >=3.6
Requires-Dist: yacs (==0.1.6)
Requires-Dist: pytorch-lightning (==0.7.6)
Requires-Dist: pretrainedmodels (>=0.7.4)
Requires-Dist: pillow (>=6.2.0)
Requires-Dist: test-tube (==0.7.5)
Requires-Dist: albumentations (>=0.4.3)
